esileapclient/__init__.py
esileapclient/common/__init__.py
esileapclient/common/base.py
esileapclient/common/utils.py
esileapclient/osc/__init__.py
esileapclient/osc/plugin.py
esileapclient/osc/v1/__init__.py
esileapclient/osc/v1/console_auth_token.py
esileapclient/osc/v1/event.py
esileapclient/osc/v1/lease.py
esileapclient/osc/v1/node.py
esileapclient/osc/v1/offer.py
esileapclient/osc/v1/mdc/__init__.py
esileapclient/osc/v1/mdc/mdc_lease.py
esileapclient/osc/v1/mdc/mdc_offer.py
esileapclient/tests/__init__.py
esileapclient/tests/functional/README.md
esileapclient/tests/functional/__init__.py
esileapclient/tests/functional/base.py
esileapclient/tests/functional/utils/__init__.py
esileapclient/tests/functional/utils/dummy_node.py
esileapclient/tests/functional/utils/esi_interfaces.py
esileapclient/tests/functional/utils/output_utils.py
esileapclient/tests/functional/v1/__init__.py
esileapclient/tests/functional/v1/test_basic.py
esileapclient/tests/functional/v1/test_policy.py
esileapclient/tests/functional/v1/test_sublease.py
esileapclient/tests/functional/v1/test_time.py
esileapclient/tests/unit/__init__.py
esileapclient/tests/unit/common/__init__.py
esileapclient/tests/unit/common/test_base.py
esileapclient/tests/unit/common/test_utils.py
esileapclient/tests/unit/osc/__init__.py
esileapclient/tests/unit/osc/test_plugin.py
esileapclient/tests/unit/osc/v1/__init__.py
esileapclient/tests/unit/osc/v1/base.py
esileapclient/tests/unit/osc/v1/fakes.py
esileapclient/tests/unit/osc/v1/test_console_auth_token.py
esileapclient/tests/unit/osc/v1/test_event.py
esileapclient/tests/unit/osc/v1/test_lease.py
esileapclient/tests/unit/osc/v1/test_node.py
esileapclient/tests/unit/osc/v1/test_offer.py
esileapclient/tests/unit/osc/v1/mdc/__init__.py
esileapclient/tests/unit/osc/v1/mdc/test_mdc_lease.py
esileapclient/tests/unit/osc/v1/mdc/test_mdc_offer.py
esileapclient/v1/__init__.py
esileapclient/v1/console_auth_token.py
esileapclient/v1/event.py
esileapclient/v1/lease.py
python_esileapclient-1.1.0.dist-info/licenses/AUTHORS
python_esileapclient-1.1.0.dist-info/licenses/LICENSE
python_esileapclient-1.1.0.dist-info/METADATA
python_esileapclient-1.1.0.dist-info/WHEEL
python_esileapclient-1.1.0.dist-info/entry_points.txt
python_esileapclient-1.1.0.dist-info/pbr.json
python_esileapclient-1.1.0.dist-info/top_level.txt
python_esileapclient-1.1.0.dist-info/RECORD
