Metadata-Version: 2.4
Name: python-esileapclient
Version: 1.1.0
Summary: ESI-LEAP CLI
Author: ESI
Author-email: esi@lists.massopen.cloud
License: Apache License, Version 2.0
Classifier: Environment :: Console
Classifier: Environment :: OpenStack
Classifier: Intended Audience :: Developers
Classifier: Intended Audience :: Information Technology
Classifier: Intended Audience :: System Administrators
Classifier: License :: OSI Approved :: Apache Software License
Classifier: Operating System :: OS Independent
Classifier: Programming Language :: Python
Classifier: Programming Language :: Python :: Implementation :: CPython
Classifier: Programming Language :: Python :: 3 :: Only
Classifier: Programming Language :: Python :: 3
Classifier: Programming Language :: Python :: 3.6
Classifier: Programming Language :: Python :: 3.7
Requires-Python: >=3.6
License-File: LICENSE
License-File: AUTHORS
Requires-Dist: openstacksdk
Requires-Dist: pbr!=2.1.0,>=2.0.0
Requires-Dist: python-openstackclient>=3.18.0
Requires-Dist: six>=1.12.0
Requires-Dist: esisdk>=1.0
Dynamic: author
Dynamic: author-email
Dynamic: classifier
Dynamic: description
Dynamic: description-content-type
Dynamic: license
Dynamic: license-file
Dynamic: requires-dist
Dynamic: requires-python
Dynamic: summary
